flake8_checkstyle/__init__.py
flake8_checkstyle/plugin.py
flake8_checkstyle-0.0.1.dist-info/DESCRIPTION.rst
flake8_checkstyle-0.0.1.dist-info/METADATA
flake8_checkstyle-0.0.1.dist-info/RECORD
flake8_checkstyle-0.0.1.dist-info/WHEEL
flake8_checkstyle-0.0.1.dist-info/entry_points.txt
flake8_checkstyle-0.0.1.dist-info/metadata.json
flake8_checkstyle-0.0.1.dist-info/top_level.txt
